sixbox/__init__.py
sixbox/backend/__init__.py
sixbox/backend/api.py
sixbox/backend/config.py
sixbox/backend/decorators.py
sixbox/backend/errors.py
sixbox/backend/version.py
sixbox/backend/http/__init__.py
sixbox/backend/http/client.py
sixbox/backend/http/error_handlers.py
sixbox/backend/meta/__init__.py
sixbox/backend/meta/collection.py
sixbox/backend/meta/comp_mutable_dict.py
sixbox/backend/meta/data.py
sixbox/backend/meta/fields.py
sixbox/backend/meta/resource.py
sixbox/backend/meta/transformer.py
sixbox/backend/models/__init__.py
sixbox/backend/models/actions.py
sixbox/backend/models/app.py
sixbox/backend/models/async_jobs.py
sixbox/backend/models/automation.py
sixbox/backend/models/billing_analysis_breakdown.py
sixbox/backend/models/billing_breakdown.py
sixbox/backend/models/billing_egress_breakdown.py
sixbox/backend/models/billing_group.py
sixbox/backend/models/billing_storage_breakdown.py
sixbox/backend/models/bulk.py
sixbox/backend/models/case.py
sixbox/backend/models/dataset.py
sixbox/backend/models/division.py
sixbox/backend/models/endpoints.py
sixbox/backend/models/enums.py
sixbox/backend/models/execution_details.py
sixbox/backend/models/file.py
sixbox/backend/models/invoice.py
sixbox/backend/models/link.py
sixbox/backend/models/marker.py
sixbox/backend/models/member.py
sixbox/backend/models/pipe.py
sixbox/backend/models/project.py
sixbox/backend/models/rate_limit.py
sixbox/backend/models/storage_export.py
sixbox/backend/models/storage_import.py
sixbox/backend/models/task.py
sixbox/backend/models/team.py
sixbox/backend/models/team_member.py
sixbox/backend/models/user.py
sixbox/backend/models/volume.py
sixbox/backend/models/compound/__init__.py
sixbox/backend/models/compound/analysis_cost.py
sixbox/backend/models/compound/analysis_cost_breakdown.py
sixbox/backend/models/compound/egress_cost.py
sixbox/backend/models/compound/error.py
sixbox/backend/models/compound/measurement.py
sixbox/backend/models/compound/price.py
sixbox-1.3.20230406093444.dist-info/LICENSE
sixbox-1.3.20230406093444.dist-info/METADATA
sixbox-1.3.20230406093444.dist-info/WHEEL
sixbox-1.3.20230406093444.dist-info/entry_points.txt
sixbox-1.3.20230406093444.dist-info/top_level.txt
sixbox-1.3.20230406093444.dist-info/RECORD
