Metadata-Version: 2.1
Name: sixbox
Version: 1.3.20230406093444
Summary: python library for sixoclock's softwares to run
Home-page: https://docs.sixoclock.net/clients/sixbox-linux.html
Author: sixoclock
Author-email: r_d@sixoclock.net
Maintainer: sixoclock
Maintainer-email: r_d@sixoclock.net
License: Apache-2.0 License
Project-URL: Documentation, https://docs.sixoclock.net/clients/sixbox-linux.html
Project-URL: Bug Tracker, https://github.com/6-oclock/Bug-Tracker/issues
Project-URL: Source Code, https://github.com/6-oclock/sixbox-linux
Platform: UNKNOWN
Requires-Python: >=3.6
Requires-Dist: pyyaml
Requires-Dist: paramiko
Requires-Dist: python-daemon
Requires-Dist: prettytable
Requires-Dist: colorlog
Requires-Dist: tqdm
Requires-Dist: oss2
Requires-Dist: filetype
Requires-Dist: cwltool
Requires-Dist: jsonpath-ng
Requires-Dist: jsonschema
Requires-Dist: shutil
Requires-Dist: hashlib
Requires-Dist: tarfile
Requires-Dist: psutil
Requires-Dist: cwltool ; "linux" in sys_platform
Requires-Dist: rdflib-jsonld ; "linux" in sys_platform
Provides-Extra: dev
Requires-Dist: pre-commit ; extra == 'dev'
Requires-Dist: pydocstyle ; extra == 'dev'
Requires-Dist: pytest ; extra == 'dev'
Requires-Dist: tox ; extra == 'dev'
